Products.ZODBFriendlyCounter-configure.zcml
setup.py
Products/__init__.py
Products.ZODBFriendlyCounter.egg-info/PKG-INFO
Products.ZODBFriendlyCounter.egg-info/SOURCES.txt
Products.ZODBFriendlyCounter.egg-info/dependency_links.txt
Products.ZODBFriendlyCounter.egg-info/entry_points.txt
Products.ZODBFriendlyCounter.egg-info/namespace_packages.txt
Products.ZODBFriendlyCounter.egg-info/not-zip-safe
Products.ZODBFriendlyCounter.egg-info/requires.txt
Products.ZODBFriendlyCounter.egg-info/top_level.txt
Products/ZODBFriendlyCounter/ZFC.py
Products/ZODBFriendlyCounter/__init__.py
Products/ZODBFriendlyCounter/changes.txt
Products/ZODBFriendlyCounter/configure.zcml
Products/ZODBFriendlyCounter/readme.txt
Products/ZODBFriendlyCounter/tests.py
Products/ZODBFriendlyCounter/version.txt
Products/ZODBFriendlyCounter/zope2.py